exp_runner/__init__.py
exp_runner/interfaces.py
exp_runner/runner.py
exp_runner/version.py
exp_runner-0.1.0b2.dist-info/LICENSE
exp_runner-0.1.0b2.dist-info/METADATA
exp_runner-0.1.0b2.dist-info/WHEEL
exp_runner-0.1.0b2.dist-info/top_level.txt
exp_runner-0.1.0b2.dist-info/RECORD
