Metadata-Version: 2.1
Name: exp-runner
Version: 0.1.0b2
Summary: Framework for data analysis and machine learning experiments
Home-page: https://github.com/slipnitskaya/exp-runner.git
Author: Sofya Lipnitskaya
Author-email: lipnitskaya.sofya@gmail.com
License: UNKNOWN
Keywords: pipeline framework modelling model training testing classification regression clustering,pipeline framework data analysis
Platform: UNKNOWN
Classifier: Development Status :: 4 - Beta
Classifier: Intended Audience :: Developers
Classifier: Intended Audience :: Education
Classifier: Intended Audience :: Other Audience
Classifier: Intended Audience :: Science/Research
Classifier: Operating System :: OS Independent
Classifier: Programming Language :: Python
Classifier: Programming Language :: Python :: 3
Classifier: Programming Language :: Python :: 3.6
Classifier: Programming Language :: Python :: 3.7
Classifier: License :: OSI Approved :: MIT License
Classifier: Topic :: Education :: Testing
Classifier: Topic :: Office/Business
Classifier: Topic :: Other/Nonlisted Topic
Classifier: Topic :: Scientific/Engineering
Classifier: Topic :: Software Development :: Libraries
Classifier: Natural Language :: English
Classifier: Typing :: Typed
Requires-Python: >=3.6
Requires-Dist: tqdm (>=4.28.1)
Requires-Dist: numpy (>=1.15.4)
Requires-Dist: scikit-learn (>=0.20.1)
